mysql/__init__.py
mysql/helper/__init__.py
xmjz/__init__.py
xmjz/common/__init__.py
xmjz/common/mysql/__init__.py
xmjz/common/mysql/helper/__init__.py
common_xmjz-0.1.3.dist-info/LICENSE
common_xmjz-0.1.3.dist-info/METADATA
common_xmjz-0.1.3.dist-info/WHEEL
common_xmjz-0.1.3.dist-info/top_level.txt
common_xmjz-0.1.3.dist-info/RECORD
