Metadata-Version: 2.1
Name: common-xmjz
Version: 0.1.3
Summary: common-xmjz
Home-page: https://github.com/me/myproject
Author: xmjz
Author-email: xxx@example.com
License: MIT
Platform: UNKNOWN
Classifier: License :: OSI Approved :: MIT License
Classifier: Programming Language :: Python
Classifier: Programming Language :: Python :: 3
Classifier: Programming Language :: Python :: 3.6
Classifier: Programming Language :: Python :: Implementation :: CPython
Classifier: Programming Language :: Python :: Implementation :: PyPy
Requires-Python: >=3.6.0
